{"cameraMode":{"drawMode":0,"name":"Shaded","section":"Shading Mode"},"sceneLighting":true,"audioPlay":false,"sceneViewState":{"m_AlwaysRefresh":false,"showFog":true,"showSkybox":true,"showFlares":true,"showImageEffects":true,"showParticleSystems":true,"showVisualEffectGraphs":true,"m_FxEnabled":true},"in2DMode":false,"pivot":{"x":0.9937971830368042,"y":0.12949681282043458,"z":3.3054542541503908},"rotation":{"x":0.41757437586784365,"y":-0.224977508187294,"z":0.1075163260102272,"w":0.8737740516662598},"size":2.2711024284362795,"orthographic":false}